odoo10_addon_product_warranty-10.0.1.0.0-py2.7-nspkg.pth
odoo/addons/product_warranty/README.rst
odoo/addons/product_warranty/__init__.py
odoo/addons/product_warranty/__manifest__.py
odoo/addons/product_warranty/demo/product_warranty.xml
odoo/addons/product_warranty/demo/res_company.xml
odoo/addons/product_warranty/i18n/es.po
odoo/addons/product_warranty/i18n/es_MX.po
odoo/addons/product_warranty/i18n/es_PA.po
odoo/addons/product_warranty/i18n/es_VE.po
odoo/addons/product_warranty/i18n/fr.po
odoo/addons/product_warranty/i18n/product_warranty.pot
odoo/addons/product_warranty/images/product_warranty.png
odoo/addons/product_warranty/models/__init__.py
odoo/addons/product_warranty/models/product_supplierinfo.py
odoo/addons/product_warranty/models/res_company.py
odoo/addons/product_warranty/models/return_instruction.py
odoo/addons/product_warranty/security/ir.model.access.csv
odoo/addons/product_warranty/tests/__init__.py
odoo/addons/product_warranty/tests/test_product_warranty.py
odoo/addons/product_warranty/views/product_warranty.xml
odoo/addons/product_warranty/views/res_company.xml
odoo10_addon_product_warranty-10.0.1.0.0.dist-info/DESCRIPTION.rst
odoo10_addon_product_warranty-10.0.1.0.0.dist-info/METADATA
odoo10_addon_product_warranty-10.0.1.0.0.dist-info/RECORD
odoo10_addon_product_warranty-10.0.1.0.0.dist-info/WHEEL
odoo10_addon_product_warranty-10.0.1.0.0.dist-info/metadata.json
odoo10_addon_product_warranty-10.0.1.0.0.dist-info/namespace_packages.txt
odoo10_addon_product_warranty-10.0.1.0.0.dist-info/top_level.txt
